rtablify/__init__.py
rtablify/__main__.py
rtablify/rtablify.py
reddit_tablify-1.0.1.dist-info/METADATA
reddit_tablify-1.0.1.dist-info/WHEEL
reddit_tablify-1.0.1.dist-info/top_level.txt
reddit_tablify-1.0.1.dist-info/RECORD
