Metadata-Version: 2.1
Name: reddit-tablify
Version: 1.0.1
Summary: Turn Python Dictionary into reddit table
Home-page: UNKNOWN
Author: Dangerforce
License: MIT
Platform: UNKNOWN
Classifier: License :: OSI Approved :: MIT License
Classifier: Programming Language :: Python :: 3
Classifier: Programming Language :: Python :: 3.7
